fields_of_gold/__init__.py
fields_of_gold/fields/__init__.py
fields_of_gold/fields/json.py
fields_of_gold/fields/related.py
fields_of_gold/tests/__init__.py
fields_of_gold/tests/base.py
fields_of_gold/tests/test_json.py
fields_of_gold-0.1.2.dist-info/LICENCE.txt
fields_of_gold-0.1.2.dist-info/METADATA
fields_of_gold-0.1.2.dist-info/WHEEL
fields_of_gold-0.1.2.dist-info/top_level.txt
fields_of_gold-0.1.2.dist-info/RECORD
