Metadata-Version: 2.1
Name: fields-of-gold
Version: 0.1.2
Summary: A Django library for providing useful DB model fields.
Home-page: https://github.com/adamalton/fields-of-gold
Author: Adam Alton
Author-email: 270255+adamalton@users.noreply.github.com
Keywords: Django,Pydantic,JSON,JSONField,Schema
Classifier: Development Status :: 4 - Beta
Classifier: Intended Audience :: Developers
Classifier: License :: OSI Approved :: BSD License
Classifier: Operating System :: OS Independent
Classifier: Programming Language :: Python
License-File: LICENCE.txt
Requires-Dist: django<6.0,>=4.2
Requires-Dist: pydantic<3.0,>2.0
